dynamic_chunks/__init__.py
dynamic_chunks/_version.py
dynamic_chunks/algorithms.py
dynamic_chunks/tests/test_algorithms.py
dynamic_chunks-0.0.3.dist-info/LICENSE
dynamic_chunks-0.0.3.dist-info/METADATA
dynamic_chunks-0.0.3.dist-info/WHEEL
dynamic_chunks-0.0.3.dist-info/top_level.txt
dynamic_chunks-0.0.3.dist-info/RECORD
