Metadata-Version: 2.1
Name: dynamic_chunks
Version: 0.0.3
Summary: Determine appropriate chunk sizes for a given xarray dataset based on target chunk size and chunk aspect ratio
Author-email: Julius Busecke <julius@ldeo.columbia.edu>
License: Apache-2.0
Project-URL: Homepage, https://github.com/jbusecke/dynamic_chunks
Project-URL: Tracker, https://github.com/jbusecke/dynamic_chunks/issues
Classifier: Development Status :: 1 - Planning
Classifier: License :: OSI Approved :: Apache Software License
Classifier: Operating System :: OS Independent
Classifier: Intended Audience :: Science/Research
Classifier: Programming Language :: Python
Classifier: Programming Language :: Python :: 3
Classifier: Programming Language :: Python :: 3.8
Classifier: Programming Language :: Python :: 3.9
Classifier: Topic :: Scientific/Engineering
Requires-Python: >=3.8
License-File: LICENSE
Requires-Dist: numpy
Requires-Dist: dask
Requires-Dist: xarray
Provides-Extra: test
Requires-Dist: pytest ; extra == 'test'
Requires-Dist: pytest-cov ; extra == 'test'
